{
  "timestamp_utc": "2026-04-04T02:23:21Z",
  "tag": "bundle_response",
  "model": "llama-3.3-70b-versatile",
  "attempt": 1,
  "mode": "bundle",
  "parse_error": null,
  "raw_output": "{\n  \"bill_of_lading\": {\n      \"bill_of_lading_number\": \"BOL-COLD-010\",\n      \"ship_from\": {\n         \"name\": \"Ice Cream Dreams\",\n         \"address\": \"1 Freezing Way\",\n         \"city_state_zip\": \"Minneapolis, MN 55401\",\n         \"sid_number\": \"SID-ICE\",\n         \"fob_point\": true\n      },\n      \"ship_to\": {\n         \"name\": \"Sweet Shop Supply\",\n         \"location_number\": \"SS-WH\",\n         \"address\": \"90 Sugar Blvd\",\n         \"city_state_zip\": \"Orlando, FL 32801\",\n         \"cid_number\": \"CID-SUG\",\n         \"fob_point\": false\n      },\n      \"carrier_details\": {\n         \"carrier_name\": \"Arctic Transport\",\n         \"trailer_number\": \"RE-100\",\n         \"seal_numbers\": \"S-1010\",\n         \"scac\": \"ARCT\",\n         \"pro_number\": \"PRO-10\",\n         \"freight_charge_terms\": \"Prepaid\"\n      },\n      \"customer_order_info\": [\n         {\n            \"order_number\": \"PO-ICE-10\",\n            \"pkgs_count\": 50,\n            \"weight\": 300.0,\n            \"pallet_slip\": true,\n            \"additional_info\": \"Insulated Containers\"\n         }\n      ],\n      \"carrier_commodity_info\": [\n         {\n            \"handling_unit_qty\": 2,\n            \"handling_unit_type\": \"Pallets\",\n            \"package_qty\": 50,\n            \"package_type\": \"Tubs\",\n            \"weight\": 300.0,\n            \"is_hazardous\": false,\n            \"commodity_description\": \"Premium Vanilla Ice Cream\",\n            \"nmfc_number\": \"NM-ICE\",\n            \"class\": \"92.5\"\n         }\n      ]\n   },\n   \"invoice\": {\n      \"invoice_number\": \"\",\n      \"seller_info\": {\n         \"company_name\": \"ZenithTech\",\n         \"address\": \"1 Innovation Blvd\",\n         \"reg_number\": \"\",\n         \"tax_number\": \"\"\n      },\n      \"bill_to_info\": {\n         \"client_name\": \"Retailer Central\",\n         \"address\": \"777 Commerce St\",\n         \"reg_number\": \"\",\n         \"tax_number\": \"\"\n      },\n      \"payment_details\": {\n         \"bank_name\": \"\",\n         \"bic\": \"\",\n         \"account_number\": \"\",\n         \"invoice_date\": \"\",\n         \"due_date\": \"\"\n      },\n      \"line_items\": [\n         {\n            \"hs_code\": \"\",\n            \"container_number\": \"CONT-Z\",\n            \"description\": \"Model Z1 Smart Device\",\n            \"quantity\": 95,\n            \"unit_of_measure\": \"\",\n            \"unit_price\": 0,\n            \"subtotal\": 0,\n            \"tax_amount\": 0,\n            \"tax_percentage\": 0\n         }\n      ],\n      \"totals\": {\n         \"subtotal\": 0,\n         \"tax_total\": 0,\n         \"grand_total\": 0,\n         \"currency\": \"\",\n         \"amount_in_words\": \"\"\n      }\n   },\n   \"packing_list\": {\n      \"delivery_to\": {\n         \"customer_name\": \"Retailer Central\",\n         \"address_lines\": [\n            \"777 Commerce St\",\n            \"Dock 1\"\n         ],\n         \"telephone\": \"555-9000\",\n         \"email\": \"logistics@retailer.com\"\n      },\n      \"from_business\": {\n         \"business_name\": \"ZenithTech\",\n         \"address_lines\": [\n            \"1 Innovation Blvd\"\n         ]\n      },\n      \"shipping_refs\": {\n         \"order_reference\": \"PO-ZEN-01\",\n         \"order_date\": \"2026-03-20\",\n         \"delivery_method\": \"Air Freight\",\n         \"delivery_number\": \"DLV-ZEN-1\",\n         \"delivery_date\": \"\"\n      },\n      \"items\": [\n         {\n            \"item_number\": \"Z1-BLACK\",\n            \"description\": \"Model Z1 Smart Device\",\n            \"qty_ordered\": 100,\n            \"qty_shipped\": 95,\n            \"weight_kg\": 475.0,\n            \"volume_cbm\": 2.0,\n            \"container_number\": \"CONT-Z\"\n         }\n      ],\n      \"notes\": \"Short shipment due to stock shortage. 5 units backordered.\"\n   },\n   \"category_metadata\": {\n      \"category\": \"Manufactured Goods\",\n      \"metadata_fields\": {\n         \"serial_number\": \"\",\n         \"model_number\": \"Z1\",\n         \"brand_name\": \"ZenithTech\",\n         \"dimensions\": {\n            \"length\": 0,\n            \"width\": 0,\n            \"height\": 0,\n            \"unit\": \"\"\n         },\n         \"warranty_period_months\": 0,\n         \"fragility_rating\": 0,\n         \"assembly_required\": false,\n         \"upc_ean_code\": \"\",\n         \"packaging_material\": \"\"\n      }\n   }\n}"
}